README.rst
setup.cfg
setup.py
asynccmd/__init__.py
asynccmd/asynccmd.py
asynccmd.egg-info/PKG-INFO
asynccmd.egg-info/SOURCES.txt
asynccmd.egg-info/dependency_links.txt
asynccmd.egg-info/top_level.txt