Metadata-Version: 1.1
Name: asynccmd
Version: 0.2.3
Summary: Asyncio implementation of Cmd Python lib.
Home-page: https://github.com/valentinmk/asynccmd
Author: Valentin Kazakov
Author-email: vkazakov@gmail.com
License: Apache 2
Download-URL: https://github.com/valentinmk/asynccmd
Platform: POSIX
Platform: Microsoft :: Windows
Classifier: License :: OSI Approved :: Apache Software License
Classifier: Programming Language :: Python :: 3.5
Classifier: Programming Language :: Python :: 3.6
Classifier: Operating System :: POSIX :: Linux
Classifier: Operating System :: Microsoft :: Windows
Classifier: Environment :: Console
Classifier: Development Status :: 3 - Alpha
Classifier: Topic :: System :: Shells
